cli_wrapper/__init__.py
cli_wrapper/cli_wrapper.py
cli_wrapper/parsers.py
cli_wrapper/transformers.py
cli_wrapper/validators.py
cli_wrapper/pre_packaged/__init__.py
cli_wrapper/util/__init__.py
cli_wrapper/util/callable_chain.py
cli_wrapper/util/callable_registry.py
cli_wrapper-0.1.0.dist-info/licenses/LICENSE.txt
help_parser/__init__.py
help_parser/__main__.py
help_parser/golang_help.py
help_parser/util.py
help_parser/validators.py
cli_wrapper-0.1.0.dist-info/METADATA
cli_wrapper-0.1.0.dist-info/WHEEL
cli_wrapper-0.1.0.dist-info/top_level.txt
cli_wrapper-0.1.0.dist-info/RECORD
