Metadata-Version: 2.4
Name: cli_wrapper
Version: 0.1.0
Summary: Tool to represent CLI tools as native python objects
Author-email: Reid Orsten <rorsten@gmail.com>
Maintainer-email: Reid Orsten <rorsten@gmail.com>
License-Expression: LGPL-3.0-or-later
Requires-Python: >=3.10
License-File: LICENSE.txt
Requires-Dist: attrs
Provides-Extra: test
Requires-Dist: pytest; extra == "test"
Requires-Dist: pytest-cov; extra == "test"
Requires-Dist: pytest-asyncio; extra == "test"
Requires-Dist: pytest-xdist; extra == "test"
Requires-Dist: ruamel.yaml; extra == "test"
Requires-Dist: dotted_dict; extra == "test"
Requires-Dist: black; extra == "test"
Requires-Dist: pylint; extra == "test"
Dynamic: license-file
